osgeo_utils/__init__.py
osgeo_utils-0.0.0.dist-info/METADATA
osgeo_utils-0.0.0.dist-info/WHEEL
osgeo_utils-0.0.0.dist-info/top_level.txt
osgeo_utils-0.0.0.dist-info/RECORD
